LICENSE.txt
README.md
setup.py
pynaroma/__init__.py
pynaroma/bin2rom.py
pynaroma/bin2split.py
pynaroma/rom2bin.py
pynaroma.egg-info/PKG-INFO
pynaroma.egg-info/SOURCES.txt
pynaroma.egg-info/dependency_links.txt
pynaroma.egg-info/entry_points.txt
pynaroma.egg-info/top_level.txt