Metadata-Version: 2.1
Name: pynaroma
Version: 0.4.0
Summary: Tools for converting Amiga ROM images
Home-page: https://github.com/shred/pynaroma
Author: Richard Körber
Author-email: dev@shredzone.de
License: GPLv3+
Project-URL: Source, https://github.com/shred/pynaroma
Project-URL: Tracker, https://github.com/shred/pynaroma/issues
Keywords: Amiga ROM
Platform: UNKNOWN
Classifier: Development Status :: 4 - Beta
Classifier: Environment :: Console
Classifier: Intended Audience :: Developers
Classifier: Intended Audience :: System Administrators
Classifier: License :: OSI Approved :: GNU General Public License v3 or later (GPLv3+)
Classifier: Operating System :: OS Independent
Classifier: Programming Language :: Python :: 3 :: Only
Classifier: Topic :: Software Development :: Build Tools
Classifier: Topic :: System :: Emulators
Classifier: Topic :: System :: Hardware
Classifier: Topic :: System :: Operating System
Classifier: Topic :: System :: Software Distribution
Classifier: Topic :: Utilities
Requires-Python: >=3
License-File: LICENSE.txt
